Metadata-Version: 2.1
Name: cwpytube
Version: 0.1.0
Summary: For download and convert YouTube videos into multi format and watch videos.
Home-page: https://github.com/zinzied/Convert-Watch-Youtube-Lib/
Author: Zied Boughdir
Author-email: Ziedboughdir@gmail.com
Classifier: Programming Language :: Python :: 3
Classifier: License :: OSI Approved :: MIT License
Classifier: Operating System :: OS Independent
Requires-Python: >=3.6
License-File: LICENSE
Requires-Dist: pytube>=10.9.3
Requires-Dist: moviepy>=1.0.3
